CHANGES.md
LICENSE.txt
MANIFEST.in
README.md
setup.py
lib/testlib.py
lib/testlib.egg-info/PKG-INFO
lib/testlib.egg-info/SOURCES.txt
lib/testlib.egg-info/dependency_links.txt
lib/testlib.egg-info/not-zip-safe
lib/testlib.egg-info/top_level.txt
test/test.py
test/test_testlib.py